rsc/__init__.py
rsc/repl.py
rsc-0.3.0.dist-info/licenses/LICENSE
rsc-0.3.0.dist-info/METADATA
rsc-0.3.0.dist-info/WHEEL
rsc-0.3.0.dist-info/top_level.txt
rsc-0.3.0.dist-info/RECORD
