Metadata-Version: 2.4
Name: rsc
Version: 0.3.0
Summary: The simplest calculator library in Python with variable support, math functions, and assignments
Author-email: Rasa8877 <letperhut@gmail.com>
License: MIT License
Project-URL: Homepage, https://github.com/Rasa8877/rs-calculator
Keywords: calculator,math,expression,variables,safe-eval,factorial,math-functions
Classifier: Programming Language :: Python :: 3
Classifier: License :: OSI Approved :: MIT License
Classifier: Operating System :: OS Independent
Requires-Python: >=3.6
License-File: LICENSE
Requires-Dist: asteval>=0.9.24
Dynamic: license-file
